factly/downloads/__init__.py
factly/downloads/config.py
factly/downloads/downloads.py
factly/downloads/wasabi_bulk_upload.py
factly/downloads/wasabi_download.py
factly/downloads/wasabi_sync_download.py
factly/downloads/wasabi_upload.py
factly_downloads-0.1.6.dist-info/METADATA
factly_downloads-0.1.6.dist-info/WHEEL
factly_downloads-0.1.6.dist-info/entry_points.txt
factly_downloads-0.1.6.dist-info/RECORD
