Metadata-Version: 2.1
Name: factly-downloads
Version: 0.1.6
Summary: 
Author: Factly Labs
Requires-Python: >=3.8,<4.0
Classifier: Programming Language :: Python :: 3
Classifier: Programming Language :: Python :: 3.8
Classifier: Programming Language :: Python :: 3.9
Classifier: Programming Language :: Python :: 3.10
Classifier: Programming Language :: Python :: 3.11
Requires-Dist: boto3 (>=1.26.159,<2.0.0)
Requires-Dist: click (>=8.0.0,<9.0.0)
Requires-Dist: pydantic (>=1.0.0,<2.0.0)
